MANIFEST.in
README.md
VERSION
requirements.txt
setup.py
mock_api/__init__.py
mock_api/support.py
mock_api.egg-info/PKG-INFO
mock_api.egg-info/SOURCES.txt
mock_api.egg-info/dependency_links.txt
mock_api.egg-info/requires.txt
mock_api.egg-info/top_level.txt