Metadata-Version: 2.1
Name: mock-api
Version: 0.0.7
Summary: mock_api
Home-page: https://github.com/remorses/TODO
Author: Tommaso De Rossi
Author-email: daer.tommy@gmail.com
License: Apache Software License 2.0
Keywords: mock_api
Platform: UNKNOWN
Classifier: Intended Audience :: Information Technology
Classifier: Programming Language :: Python :: 3
Classifier: Programming Language :: Python :: 3.6
Classifier: Programming Language :: Python :: 3.7
